{
	"guest":[
		{
			"id" : "1",
			"info": 
				{
					"first_name" : "Stephen",
					"last_name" : "Smith",
					"email" : "stephen@event.com",
					"note" : "The Smiths",
					"isComing" : "1"
				},
			"question":
				[
					{
						"question_id":"1",
						"answer":"Chicken"
					},
					{
						"question_id":"2",
						"answer":"Yes"
					}
				],
			"plus_one":{
					"info":{
							"first_name" : "Plussy",
							"last_name" : "Juan",
							"email" : "pjuan@event.com",
							"note" : "The Smiths",
							"code" : "12345",
							"event_id":"1",
							"guest_id":"3",
							"party_id":"1",
							"allowedGuest":"0"
					},
					"question":
					[
						{
							"question_id":"1",
							"answer":"Beef"
						},
						{
							"question_id":"2",
							"answer":"No"
						}
					]

				}	
		},
		{
			"id" : "2",
			"info": 
				{
					"first_name" : "Stephen",
					"last_name" : "Smith",
					"email" : "stephen@event.com",
					"note" : "The Smiths",
					"isComing" : "0"
				},
			"question":
				[
					{
						"question_id":"",
						"answer":""
					},
					{
						"question_id":"",
						"answer":""
					}
				],
			"plus_one" : {}
			
		}
	]
}